augmentry/__init__.py
augmentry/client.py
augmentry/exceptions.py
augmentry-1.1.0.dist-info/licenses/LICENSE
augmentry-1.1.0.dist-info/METADATA
augmentry-1.1.0.dist-info/WHEEL
augmentry-1.1.0.dist-info/top_level.txt
augmentry-1.1.0.dist-info/RECORD
