Metadata-Version: 2.4
Name: augmentry
Version: 1.1.0
Summary: Official Python SDK for the Augmentry API
Home-page: https://github.com/augmentry/augmentry-python-sdk
Author: Augmentry Team
Author-email: Augmentry Team <support@augmentry.io>
License-Expression: MIT
Project-URL: Homepage, https://github.com/augmentry/augmentry-python-sdk
Project-URL: Documentation, https://docs.augmentry.io
Project-URL: Repository, https://github.com/augmentry/augmentry-python-sdk
Project-URL: Bug Reports, https://github.com/augmentry/augmentry-python-sdk/issues
Keywords: augmentry,api,sdk,solana,crypto,trading,analytics
Classifier: Development Status :: 4 - Beta
Classifier: Intended Audience :: Developers
Classifier: Operating System :: OS Independent
Classifier: Programming Language :: Python :: 3
Classifier: Programming Language :: Python :: 3.8
Classifier: Programming Language :: Python :: 3.9
Classifier: Programming Language :: Python :: 3.10
Classifier: Programming Language :: Python :: 3.11
Classifier: Programming Language :: Python :: 3.12
Requires-Python: >=3.8
License-File: LICENSE
Requires-Dist: aiohttp>=3.8.0
Provides-Extra: dev
Requires-Dist: pytest>=7.0.0; extra == "dev"
Requires-Dist: pytest-asyncio>=0.21.0; extra == "dev"
Requires-Dist: pytest-cov>=4.0.0; extra == "dev"
Requires-Dist: black>=23.0.0; extra == "dev"
Requires-Dist: isort>=5.12.0; extra == "dev"
Requires-Dist: flake8>=6.0.0; extra == "dev"
Requires-Dist: mypy>=1.0.0; extra == "dev"
Dynamic: author
Dynamic: home-page
Dynamic: license-file
Dynamic: requires-python
